jormungandr/__init__.py
jormungandr/client.py
jormungandr-0.0.1.dist-info/LICENSE.txt
jormungandr-0.0.1.dist-info/METADATA
jormungandr-0.0.1.dist-info/WHEEL
jormungandr-0.0.1.dist-info/top_level.txt
jormungandr-0.0.1.dist-info/RECORD
