Metadata-Version: 2.1
Name: jormungandr
Version: 0.0.1
Summary: Python wrapper for ThorChain Midgard API
Home-page: https://https://gitlab.com/JormThor/Jormungandr/jormthor/Jormungandr
Author: Jorm Thor
Author-email: jormthor@protonmail.com
License: MIT
Project-URL: Documentation, https://Jormungandr.readthedocs.io/
Project-URL: Changelog, https://Jormungandr.readthedocs.io/en/latest/changelog.html
Project-URL: Issue Tracker, https://https://gitlab.com/JormThor/Jormungandr/jormthor/Jormungandr/issues
Platform: UNKNOWN
Classifier: Development Status :: 5 - Production/Stable
Classifier: Intended Audience :: Developers
Classifier: Operating System :: Unix
Classifier: Operating System :: POSIX
Classifier: Operating System :: Microsoft :: Windows
Classifier: Programming Language :: Python
Classifier: Programming Language :: Python :: 3
Classifier: Programming Language :: Python :: 3 :: Only
Classifier: Programming Language :: Python :: 3.6
Classifier: Programming Language :: Python :: 3.7
Classifier: Programming Language :: Python :: 3.8
Classifier: Programming Language :: Python :: 3.9
Classifier: Programming Language :: Python :: Implementation :: CPython
Classifier: Programming Language :: Python :: Implementation :: PyPy
Classifier: Topic :: Utilities
Requires-Python: >=3.6
